pandas_transformers-0.2.3.dist-info/DESCRIPTION.rst
pandas_transformers-0.2.3.dist-info/METADATA
pandas_transformers-0.2.3.dist-info/RECORD
pandas_transformers-0.2.3.dist-info/WHEEL
pandas_transformers-0.2.3.dist-info/metadata.json
pandas_transformers-0.2.3.dist-info/top_level.txt
pd_tran/__init__.py
pd_tran/pipeline.py
pd_tran/feature_extraction/__init__.py
pd_tran/feature_extraction/date.py
pd_tran/feature_selection/__init__.py
pd_tran/feature_selection/manual_selector.py
pd_tran/filters/__init__.py
pd_tran/filters/date.py
pd_tran/filters/text.py
pd_tran/preprocessing/__init__.py
pd_tran/preprocessing/converter.py
pd_tran/preprocessing/text.py
